{
  "packages":
  [
    {
      "name": "wonkystuffCore",
      "maintainer": "wonkystuff",
      "websiteURL": "https://wonkystuff.net",
      "email" : "info@wonkystuff.net",
      "platforms":
      [
        {
          "name": "Wonkystuff Core1",
          "architecture": "avr",
          "version": "0.0.1",
          "category": "Contributed",
          "url": "https://wonkystuff-uk.github.io/arduino/wonkystuffCore-0.0.1.zip",
          "archiveFileName": "wonkystuffCore-0.0.1.zip",
          "checksum": "SHA-256:3e613b43e454f97ec7305d797ddaed98dfab214f65dbc65d5e4014dd146ac734",
          "size": "88821",
          "boards": [
            {
              "name": "Wonkystuff Core1 Rev.D"
            }
          ],
          "toolsDependencies":
          [
            {
                "packager": "arduino",
                "name": "avr-gcc",
                "version": "7.3.0-atmel3.6.1-arduino7"
            }
          ]
        },
        {
            "name": "Wonkystuff Core1",
            "architecture": "avr",
            "version": "0.0.2",
            "category": "Contributed",
            "url": "https://wonkystuff-uk.github.io/arduino/wonkystuffCore-0.0.2.zip",
            "archiveFileName": "wonkystuffCore-0.0.2.zip",
            "checksum": "SHA-256:f27034f4263ba2f01ce6efe9f57013e585a26b3ea26260cf66ec23bd5afb39dd",
            "size": "94974",
            "boards": [
              {
                "name": "Wonkystuff Core1 Rev.D"
              }
            ],
            "toolsDependencies":
            [
              {
                  "packager": "arduino",
                  "name": "avr-gcc",
                  "version": "7.3.0-atmel3.6.1-arduino7"
              }
            ]
          }
      ],
      "tools":
      [
      ]
    }
  ]
}